sage/libs/__init__.py
sage/libs/__init__.pyc
sage/libs/_version.py
sage/libs/_version.pyc
sage/libs/py.typed
sage/libs/__pycache__/__init__.cpython-311.pyc
sage/libs/__pycache__/_version.cpython-311.pyc
sage/libs/agentic/__init__.py
sage/libs/agentic/__init__.pyc
sage/libs/agentic/__pycache__/__init__.cpython-311.pyc
sage/libs/agentic/interface/__init__.py
sage/libs/agentic/interface/__init__.pyc
sage/libs/agentic/interface/base.pyc
sage/libs/agentic/interface/factory.pyc
sage/libs/agentic/interface/__pycache__/__init__.cpython-311.pyc
sage/libs/agentic/interface/__pycache__/base.cpython-311.pyc
sage/libs/agentic/interface/__pycache__/factory.cpython-311.pyc
sage/libs/amms/README.md
sage/libs/amms/__init__.py
sage/libs/amms/__init__.pyc
sage/libs/amms/__pycache__/__init__.cpython-311.pyc
sage/libs/amms/interface/__init__.py
sage/libs/amms/interface/__init__.pyc
sage/libs/amms/interface/base.pyc
sage/libs/amms/interface/factory.pyc
sage/libs/amms/interface/registry.pyc
sage/libs/amms/interface/__pycache__/__init__.cpython-311.pyc
sage/libs/amms/interface/__pycache__/base.cpython-311.pyc
sage/libs/amms/interface/__pycache__/factory.cpython-311.pyc
sage/libs/amms/interface/__pycache__/registry.cpython-311.pyc
sage/libs/amms/wrappers/__init__.py
sage/libs/amms/wrappers/__init__.pyc
sage/libs/ann/__init__.py
sage/libs/ann/__init__.pyc
sage/libs/ann/__pycache__/__init__.cpython-311.pyc
sage/libs/ann/interface/__init__.py
sage/libs/ann/interface/__init__.pyc
sage/libs/ann/interface/base.pyc
sage/libs/ann/interface/factory.pyc
sage/libs/ann/interface/__pycache__/__init__.cpython-311.pyc
sage/libs/ann/interface/__pycache__/base.cpython-311.pyc
sage/libs/ann/interface/__pycache__/factory.cpython-311.pyc
sage/libs/ann/interface/implementations/__init__.py
sage/libs/ann/interface/implementations/__init__.pyc
sage/libs/ann/interface/implementations/dummy.pyc
sage/libs/dataops/__init__.py
sage/libs/dataops/__init__.pyc
sage/libs/dataops/json_ops.pyc
isage_libs-0.2.2.1.dist-info/METADATA
isage_libs-0.2.2.1.dist-info/WHEEL
isage_libs-0.2.2.1.dist-info/top_level.txt
isage_libs-0.2.2.1.dist-info/RECORD
