Metadata-Version: 2.4
Name: isage-libs
Version: 0.2.2.1
Summary: SAGE Libraries - Streaming-Augmented Generative Execution
Author-email: IntelliStream Team <shuhao_zhang@hust.edu.cn>
License: MIT
Project-URL: Homepage, https://github.com/intellistream/SAGE
Project-URL: Documentation, https://intellistream.github.io/SAGE-Pub/
Project-URL: Repository, https://github.com/intellistream/SAGE.git
Project-URL: Bug Tracker, https://github.com/intellistream/SAGE/issues
Keywords: applications,examples,templates,rag,agents,streaming,tutorials,sage
Classifier: Development Status :: 4 - Beta
Classifier: Intended Audience :: Developers
Classifier: Topic :: Software Development :: Libraries :: Python Modules
Classifier: Topic :: Scientific/Engineering :: Artificial Intelligence
Classifier: Topic :: System :: Distributed Computing
Requires-Python: >=3.10
Requires-Dist: numpy<2.3.0,>=1.26.0
Requires-Dist: isage-common>=0.2.0
Provides-Extra: dev
Requires-Dist: pytest>=7.4.0; extra == "dev"
Requires-Dist: pytest-cov>=4.0.0; extra == "dev"
Requires-Dist: pytest-asyncio>=0.21.0; extra == "dev"
Requires-Dist: ruff==0.14.6; extra == "dev"
Requires-Dist: mypy>=1.7.0; extra == "dev"
Provides-Extra: anns
Requires-Dist: isage-anns>=0.1.0; extra == "anns"
Provides-Extra: amms
Requires-Dist: isage-amms>=0.1.0; extra == "amms"
Provides-Extra: finetune
Requires-Dist: isage-finetune>=0.1.0; extra == "finetune"
Provides-Extra: agentic
Requires-Dist: isage-agentic>=0.1.0; extra == "agentic"
Provides-Extra: rag
Requires-Dist: isage-rag>=0.1.0; extra == "rag"
Provides-Extra: eval
Requires-Dist: isage-eval>=0.1.0; extra == "eval"
Provides-Extra: privacy
Requires-Dist: isage-privacy>=0.1.0; extra == "privacy"
Provides-Extra: safety
Requires-Dist: isage-safety>=0.1.0; extra == "safety"
Provides-Extra: vdb
Requires-Dist: chromadb>=1.0.20; extra == "vdb"
Requires-Dist: pymilvus[model]>=2.4.0; extra == "vdb"
Provides-Extra: streaming
Requires-Dist: kafka-python>=2.0.0; extra == "streaming"
Requires-Dist: redis>=4.0.0; extra == "streaming"
Provides-Extra: notebook
Requires-Dist: jupyter>=1.0.0; extra == "notebook"
Requires-Dist: notebook>=6.0.0; extra == "notebook"
Provides-Extra: metrics
Requires-Dist: datasets>=2.0.0; extra == "metrics"
Requires-Dist: evaluate>=0.4.0; extra == "metrics"
Requires-Dist: rouge>=1.0.0; extra == "metrics"
Requires-Dist: rouge-score>=0.1.0; extra == "metrics"
Requires-Dist: bleu>=0.3.0; extra == "metrics"
Provides-Extra: loaders
Requires-Dist: PyPDF2>=3.0.0; extra == "loaders"
Requires-Dist: python-docx>=0.8.11; extra == "loaders"
Provides-Extra: ocr
Requires-Dist: easyocr>=1.7.0; extra == "ocr"
Provides-Extra: llm
Requires-Dist: isagellm>=0.1.0; extra == "llm"
Requires-Dist: transformers<4.54.0,>=4.52.0; extra == "llm"
Requires-Dist: tokenizers<0.24.0,>=0.21.0; extra == "llm"
Requires-Dist: torch<3.0.0,>=2.7.0; extra == "llm"
Requires-Dist: sentence-transformers<4.0.0,>=3.1.0; extra == "llm"
Provides-Extra: training
Requires-Dist: peft<1.0.0,>=0.18.0; extra == "training"
Requires-Dist: accelerate<2.0.0,>=1.9.0; extra == "training"
Requires-Dist: tensorboard>=2.14.0; extra == "training"
Requires-Dist: trl<0.21.0,>=0.20.0; extra == "training"
Provides-Extra: all
Requires-Dist: isage-libs[agentic,amms,anns,dev,finetune,llm,loaders,metrics,notebook,ocr,privacy,rag,safety,streaming,training,vdb]; extra == "all"
